pie_documents/__init__.py
pie_documents/annotations.py
pie_documents/document/__init__.py
pie_documents/document/processing/__init__.py
pie_documents/document/processing/merge_multi_spans.py
pie_documents/document/processing/merge_spans_via_relation.py
pie_documents/document/processing/regex_partitioner.py
pie_documents/document/processing/relation_argument_sorter.py
pie_documents/document/processing/sentence_splitter.py
pie_documents/document/processing/text_pair.py
pie_documents/document/processing/text_span_trimmer.py
pie_documents/document/processing/tokenization.py
pie_documents/documents.py
pie_documents/metrics/__init__.py
pie_documents/metrics/confusion_matrix.py
pie_documents/metrics/f1.py
pie_documents/metrics/relation_argument_distance_collector.py
pie_documents/metrics/span_coverage_collector.py
pie_documents/metrics/span_length_collector.py
pie_documents/metrics/squad_f1.py
pie_documents/metrics/statistics.py
pie_documents/models/base_models/bart_as_pointer_network.py
pie_documents/models/components/pooler.py
pie_documents/taskmodules/common/__init__.py
pie_documents/taskmodules/cross_text_binary_coref.py
pie_documents/utils/__init__.py
pie_documents/utils/sequence_tagging/__init__.py
pie_documents/utils/sequence_tagging/convert_annotation.py
pie_documents/utils/sequence_tagging/encoding.py
pie_documents/utils/sequence_tagging/ill_formed.py
pie_documents/utils/span.py
pie_documents-0.1.0.dist-info/METADATA
pie_documents-0.1.0.dist-info/WHEEL
pie_documents-0.1.0.dist-info/licenses/LICENSE
pie_documents-0.1.0.dist-info/RECORD
