Metadata-Version: 2.4
Name: pie-documents
Version: 0.1.0
Summary: Python-IE document and annotation types as well as document processing utilities
License-File: LICENSE
Author: Arne Binder
Author-email: arne.binder@dfki.de
Requires-Python: >=3.9,<4.0
Classifier: Framework :: Pytest
Classifier: Programming Language :: Python
Classifier: Programming Language :: Python :: 3
Classifier: Programming Language :: Python :: 3.9
Classifier: Programming Language :: Python :: 3.10
Classifier: Programming Language :: Python :: 3.11
Classifier: Programming Language :: Python :: 3.12
Classifier: Programming Language :: Python :: 3.13
Classifier: Programming Language :: Python :: 3.14
Classifier: Programming Language :: Python :: 3 :: Only
Requires-Dist: pandas (>=2.0.3,<3.0.0)
Requires-Dist: pie-core (>=0.2.0,<0.4.0)
Project-URL: Bug Tracker, https://github.com/arnebinder/pie-documents/issues
Project-URL: Changelog, https://github.com/arnebinder/pie-documents/releases
Project-URL: Homepage, https://github.com/arnebinder/pie-documents
Project-URL: Repository, https://github.com/arnebinder/pie-documents
